moside-0.1.6.dist-info/METADATA
moside-0.1.6.dist-info/WHEEL
moside-0.1.6.dist-info/entry_points.txt
moside-0.1.6.dist-info/licenses/LICENSE
moside/__init__.py
moside/assets/__init__.py
moside/assets/i18n/modern_main_window_en_US.qm
moside/assets/i18n/modern_main_window_en_US.ts
moside/assets/i18n/modern_main_window_zh_CN.qm
moside/assets/i18n/modern_main_window_zh_CN.ts
moside/assets/resources.py
moside/assets/resources.qrc
moside/assets/themes/dracula/icons/cil-3d.png
moside/assets/themes/dracula/icons/cil-4k.png
moside/assets/themes/dracula/icons/cil-account-logout.png
moside/assets/themes/dracula/icons/cil-action-redo.png
moside/assets/themes/dracula/icons/cil-action-undo.png
moside/assets/themes/dracula/icons/cil-airplane-mode-off.png
moside/assets/themes/dracula/icons/cil-airplane-mode.png
moside/assets/themes/dracula/icons/cil-alarm.png
moside/assets/themes/dracula/icons/cil-align-center.png
moside/assets/themes/dracula/icons/cil-align-left.png
moside/assets/themes/dracula/icons/cil-align-right.png
moside/assets/themes/dracula/icons/cil-arrow-bottom-2.png
moside/assets/themes/dracula/icons/cil-arrow-bottom.png
moside/assets/themes/dracula/icons/cil-arrow-circle-bottom.png
moside/assets/themes/dracula/icons/cil-arrow-circle-left.png
moside/assets/themes/dracula/icons/cil-arrow-circle-right.png
moside/assets/themes/dracula/icons/cil-arrow-circle-top.png
moside/assets/themes/dracula/icons/cil-arrow-left.png
moside/assets/themes/dracula/icons/cil-arrow-left2.png
moside/assets/themes/dracula/icons/cil-arrow-right.png
moside/assets/themes/dracula/icons/cil-arrow-right2.png
moside/assets/themes/dracula/icons/cil-arrow-top.png
moside/assets/themes/dracula/icons/cil-arrow-top2.png
moside/assets/themes/dracula/icons/cil-at.png
moside/assets/themes/dracula/icons/cil-av-timer.png
moside/assets/themes/dracula/icons/cil-ban.png
moside/assets/themes/dracula/icons/cil-battery-0.png
moside/assets/themes/dracula/icons/cil-battery-3.png
moside/assets/themes/dracula/icons/cil-battery-5.png
moside/assets/themes/dracula/icons/cil-battery-alert.png
moside/assets/themes/dracula/icons/cil-battery-slash.png
moside-0.1.6.dist-info/RECORD
