Metadata-Version: 2.1
Name: moside
Version: 0.1.6
Summary: Modern Pyside6！！！无学习成本，傻瓜化使用，快速为您的PySide6项目添加现代UI和实用的功能。
Author-Email: =?utf-8?b?5rGf55m95rKz?= <baiheqiuhan@qq.com>
License: GPL-3.0
Requires-Python: <3.12,>=3.8
Requires-Dist: pydantic>=2.9.2
Requires-Dist: pywin32; sys_platform == "win32"
Requires-Dist: colorlog>=6.9.0
Requires-Dist: loguru>=0.7.2
